{
    "expression": "goof _____",
    "today": "November 30th, 2025",
    "date_fr": "30 novembre 2025",
    "date_es": "30 de noviembre de 2025",
    "date_it": "30 novembre 2025",
    "date_ru": "30 \u043d\u043e\u044f\u0431\u0440\u044f 2025 \u0433.",
    "past_terms_1": {
        "date": "November 18th",
        "date_fr": "18 novembre",
        "date_es": "18 de noviembre",
        "date_it": "18 novembre",
        "date_ru": "18 \u043d\u043e\u044f\u0431\u0440\u044f 2025 \u0433.",
        "term": "gibberish"
    },
    "past_terms_2": {
        "date": "November 19th",
        "date_fr": "19 novembre",
        "date_es": "19 de noviembre",
        "date_it": "19 novembre",
        "date_ru": "19 \u043d\u043e\u044f\u0431\u0440\u044f 2025 \u0433.",
        "term": "swiftly"
    },
    "past_terms_3": {
        "date": "November 20th",
        "date_fr": "20 novembre",
        "date_es": "20 de noviembre",
        "date_it": "20 novembre",
        "date_ru": "20 \u043d\u043e\u044f\u0431\u0440\u044f 2025 \u0433.",
        "term": "rotten to the core"
    },
    "past_terms_4": {
        "date": "November 25th",
        "date_fr": "25 novembre",
        "date_es": "25 de noviembre",
        "date_it": "25 novembre",
        "date_ru": "25 \u043d\u043e\u044f\u0431\u0440\u044f 2025 \u0433.",
        "term": "joined at the hip"
    }
}